Workbook

Sheet Start Here
B2: CREATYV — Operational Cost & Pricing Readiness Model
B4: What this is
B5: Before pricing gets discussed with anyone — a client, an investor, or even yourself — this workbook exists to answer one question honestly: what does it actually cost, in rupees, to run CREATYV for one more client? Every number in this sheet came from what's actually built in the codebase. The blank yellow cells are the ones only you can fill in, because they're vendor prices that live in a Render/Supabase/OpenRouter dashboard, not in the code.
B7: How to use it
B8: 1. Go to "1. Fixed Infra Costs" and fill in the yellow cells with your real monthly bills — Render, Supabase, Redis, Vercel, domain, WhatsApp/Meta if billed.
B9: 2. Go to "2. AI Variable Costs" and fill in what OpenRouter/Replicate actually charge per model, and a rough guess at how many generations an average client uses per month.
B10: 3. Go to "3. Client Economics" and fill in how many active clients you have (or expect) and today's membership price. The sheet will calculate your real cost per client and real margin automatically.
B11: 4. Go to "4. Open Decisions" and work through the contradictions found in the code — these are business decisions waiting on you, not bugs waiting on a developer.
B12: 5. Once this whole sheet feels true, you're ready to sit down with the founder-guide money section and actually answer it with numbers instead of guesses.
B14: Color key
B15: Yellow cells = numbers only you can fill in (real vendor prices, real usage)
B16: Blue text = an assumption you can change to test a scenario
... B20: Live exchange rate (this one cell drives every USD-based cost in the workbook)
B21: 1 US Dollar (USD) = | C21: 95.43 | D21: ← update this whenever the rupee moves
B22: Every vendor cost quoted in US dollars in Sheets 1–3 (Render, Redis, Supabase, OpenRouter/AI model pricing, S3/Supabase storage) is now a formula that multiplies the vendor's real USD price by this cell. Change C21 and the whole workbook — Sheet 4 margins included — recalculates instantly. WhatsApp and Razorpay rates are quoted directly in INR/%% by Meta/Razorpay for India, so they are not tied to this rate.

Sheet 1. Fixed Infra Costs
A1: Fixed Monthly Infrastructure Costs
A2: These run whether you have 1 client or 500. Render has been fully retired, Redis is now on Upstash, and file storage is now confirmed live on Cloudflare R2 — all three migrations are done, not planned. Both columns below now show the same confirmed numbers; kept as two columns so this sheet is ready to compare against the next real infra decision, whenever that comes up.
A4: Item | B4: What it's actually used for (from the code) | C4: Now (Railway + Upstash + R2) | D4: Planned (Railway + Upstash + R2) | E4: Notes
A5: Backend hosting (web service + 4 background workers) | B5: Runs server.js: the API plus the social publish, AI generation, fulfillment monitor, and event outbox workers — all always-on. This is the line item that actually changes with the Railway move. | C5: 474 | D5: =10*'Start Here'!$C$21 -> 954.3 | E5: Confirmed: deployed on Railway’s Hobby plan ($5/mo base + $5 included usage credit). $10/mo is a realistic working estimate at current scale — swap in your exact Railway billing dashboard number once you’ve got a few weeks of real usage data.
A6: Redis | B6: Powers BullMQ job queues and live/SSE notifications. Required either way — decide if this moves to Railway's managed Redis or stays separate. | C6: 0 | D6: 0 | E6: Confirmed: Upstash free tier — 10,000 commands/sec, 256MB data, 50GB monthly bandwidth, ₹0/month. Singapore region, co-located with the Railway backend. Plenty of headroom at current scale.
A7: Supabase — Postgres | B7: Main database, accessed via Supabase's session pooler. This isn't part of your stated migration — assume it stays on Supabase in both columns unless that changes too. | C7: 0 | D7: =25*'Start Here'!$C$21 -> 2385.75 | E7: Supabase Pro is $25/mo flat, bundling Postgres compute (Micro instance covered by included credit), auth, and a storage/bandwidth allowance. Same in both columns since the DB isn't part of the stated migration. If your DB has outgrown the Micro instance, add a compute upgrade on top of this. Cell now = $25 × the exchange rate on Start Here (same both columns).
A8: File storage (Mintbox + avatars + KYC + job files) | B8: Confirmed live on Cloudflare R2 (verified: a real uploaded file is showing correctly in the R2 dashboard). | C8: 0 | D8: 0 | E8: Left at ₹0 here on purpose — storage is modeled per-GB in Sheet 3 instead of as a flat guess, since it scales with how much clients actually upload. Sheet 3 now carries the confirmed R2 per-GB rate.
A9: Vercel — frontend hosting | B9: Hosts the client-facing app. Unrelated to the backend/storage migration — usually the same in both columns. | C9: 0 | D9: 0 | E9: Vercel's Hobby tier is free and typically sufficient for a single-team SPA at this stage — set to ₹0. Upgrade to Pro (~$20/mo) only if you need team seats or hit bandwidth limits.
A10: Domain / DNS / misc | B10: Domain renewal, CDN, email sending, etc. | E10: No public pricing to look up here — this is genuinely yours to fill in from your own domain/email bills.
A12: Total Fixed Monthly Cost | C12: =SUM(C5:C10) -> 474 | D12: =SUM(D5:D10) -> 3340.05

Sheet 2. AI Variable Costs
A1: AI (Mint AI) Variable Costs Per Client
A2: These scale with usage, not with client count alone. Fill in the actual OpenRouter/Replicate price per unit (yellow), and a realistic guess at monthly usage per active client (yellow). The model estimates monthly AI cost per client automatically.
A4: Model (as configured in DB) | B4: Type | C4: Your cost per unit | D4: Unit | E4: Avg uses / client / month | F4: Est. monthly cost / client
A5: openai/gpt-4o-mini | B5: Text | C5: =0.000375*'Start Here'!$C$21 -> 0.03578625 | D5: per 1K tokens | E5: 8 | F5: =IFERROR(C5*E5,0) -> 0.28629
A6: openai/gpt-4o | B6: Text | C6: =0.006251*'Start Here'!$C$21 -> 0.59653293 | D6: per 1K tokens | E6: 4 | F6: =IFERROR(C6*E6,0) -> 2.3861317
A7: anthropic/claude-3-haiku | B7: Text | C7: =0.000749*'Start Here'!$C$21 -> 0.07147707 | D7: per 1K tokens | E7: 6 | F7: =IFERROR(C7*E7,0) -> 0.42886242
A8: anthropic/claude-3.5-sonnet | B8: Text | C8: =0.009*'Start Here'!$C$21 -> 0.85887 | D8: per 1K tokens | E8: 3 | F8: =IFERROR(C8*E8,0) -> 2.57661
A9: google/gemini-flash-1.5 | B9: Text | C9: =0.000188*'Start Here'!$C$21 -> 0.01794084 | D9: per 1K tokens | E9: 6 | F9: =IFERROR(C9*E9,0) -> 0.10764504
A10: google/gemini-2.5-flash-image | B10: Image | C10: =0.04*'Start Here'!$C$21 -> 3.8172 | D10: per image | E10: 3 | F10: =IFERROR(C10*E10,0) -> 11.4516
A11: google/veo-3.1 / veo-3.1-fast / veo-3.1-lite | B11: Video | C11: =0.75*'Start Here'!$C$21 -> 71.5725 | D11: per video | E11: 1 | F11: =IFERROR(C11*E11,0) -> 71.5725
A12: openai/sora-2-pro | B12: Video | C12: =2*'Start Here'!$C$21 -> 190.86 | D12: per video | E12: 1 | F12: =IFERROR(C12*E12,0) -> 190.86
A13: bytedance/seedance-1-5-pro | B13: Video | C13: =0.4*'Start Here'!$C$21 -> 38.172 | D13: per video | E13: 1 | F13: =IFERROR(C13*E13,0) -> 38.172
A14: Replicate (any other model used) | B14: Mixed | C14: 0 | D14: per call | E14: 0 | F14: =IFERROR(C14*E14,0) -> 0
A16: Total estimated AI cost per client / month | F16: =SUM(F5:F14) -> 317.84164
A18: Quota fields in the code (text_generations, image_generations, video_generations under membership.trial and elsewhere) cap how many a client can use — but nothing in the code currently converts those caps into a rupee cost. That conversion only exists here, once you fill in real prices.
A20: Rates above are blended averages from published July 2026 pricing (OpenRouter model pages, Google/OpenAI video pricing guides), converted at ~₹83/$1. Seedance-1-5-pro's rate could not be confirmed from a primary source — treat that one row as a rough placeholder. “Avg uses/client/month” starts from the trial quotas Codex found in the code (10 text, 3 image generations) as a reasonable first guess — replace with real usage once you have it. Each rate above is now a formula (USD price × the exchange-rate cell on "Start Here") instead of a fixed rupee number, so it updates automatically as the rupee moves.

Sheet 3. Other Per-Client Costs
A1: Storage, Payments & Third-Party Costs Per Client
A2: The other costs that scale per client, beyond AI.
A4: Item | B4: What it actually is (from the code) | C4: Now (Cloudflare R2) | D4: Now (Cloudflare R2) | E4: Est. cost / client / month | F4: Notes
A5: Storage (Mintbox + avatars + KYC + job files) | B5: Grows with every file a client uploads. Enter ₹ per GB/month for each provider, and an assumed average GB per client. | C5: =0.015*'Start Here'!$C$21 -> 1.43145 | D5: =0.015*'Start Here'!$C$21 -> 1.43145 | E5: Fill “avg GB/client” in Sheet 4 note; cost = rate × GB | F5: Confirmed: file storage is live on Cloudflare R2 at ~$0.015/GB/month storage, verified via a real uploaded reference file appearing correctly in the R2 dashboard (private bucket rules holding, matching the KYC/mintbox privacy fix from before the migration). R2’s bigger win over Supabase/S3 is $0 egress — every client download is free, versus ~$0.09/GB on S3. Worth double-checking the other three buckets (avatars, kyc-docs, job-attachments) show the same confirmed activity before considering the full migration complete — this cell reflects the storage rate either way.
A6: Razorpay payment processing fee | B6: Real Razorpay integration exists for membership + access pass checkout. No fee % is hard-coded in the live backend — confirm your actual merchant rate. | C6: 0.0236 | D6: 0.0236 | E6: Modeled against revenue in Sheet 4 | F6: Razorpay's standard published India rate is 2% MDR + 18% GST on that fee, ≈2.36% effective on domestic cards/UPI/netbanking. Same regardless of hosting migration.
A7: WhatsApp (Meta) — Utility rate (project-status messages we send) | B7: Real WhatsApp send/webhook integration exists. This is the rate Meta charges when WE message the client first — e.g. "your project moved to production" — not when they reply to us. Replies inside an open 24-hour customer window are free. | C7: 0.115 | D7: 0.115 | E7: Modeled in Sheet 4 — cost = this rate × utility messages sent per client/month. | F7: Meta's 2026 India rate for Utility (business-initiated, non-promotional) messages is ₹0.115/message — authentication messages are priced the same. Same rate regardless of the Railway/S3 migration, since Meta bills per message, not per host.
A8: WhatsApp (Meta) — Marketing rate ("normal"/promotional messages) | B8: If you ever send broadcast promos, re-engagement nudges, or any non-utility announcement, Meta bills these at the higher Marketing rate instead. | C8: 0.8631 | D8: 0.8631 | E8: Modeled in Sheet 4 — cost = this rate × marketing messages sent per client/month (defaults to 0). | F8: Meta's 2026 India Marketing rate is ₹0.8631/message — about 7.5× the Utility rate. Meta raised this rate ~10% on Jan 1, 2026 (from ₹0.7846). Only give this a volume in Sheet 4 if you actually plan to send promotional broadcasts, not project updates.
A9: Meta/Facebook & Instagram publishing | B9: Real posting + rate-limit handling exists. Meta's Graph API is free at normal volumes. | C9: 0 | D9: 0 | E9: =IFERROR(C9,0) -> 0 | F9: No paid tier found in code.
A10: YouTube Data API | B10: Real video upload integration exists. Free up to a daily quota; paid increases exist if you outgrow it. | C10: 0 | D10: 0 | E10: =IFERROR(C10,0) -> 0 | F10: Likely ₹0 unless you request a quota increase.

Sheet 4. Client Economics
A1: Cost & Margin Per Client — Current vs Planned, Side by Side
A2: Fill in the yellow cells across Sheets 1–3 first. Railway, Upstash, and Cloudflare R2 are all now confirmed live, so the infra numbers behind this page are real, not estimates. These two columns now compare two client-scale scenarios side by side (30 clients vs 100 clients) — change the inputs below to model whatever scale question matters to you right now.
B4: Current | C4: Planned
A5: Inputs
A6: Number of active clients | B6: 30 | C6: 100
A7: Monthly membership price (₹999 today) | B7: 999 | C7: 999
A8: Avg. storage per client (GB/month) | B8: 10 | C8: 10
A9: Avg active projects per client per month | B9: 10 | C9: 15
A10: Status-update (Utility) messages we send per project | B10: 10 | C10: 10
A11: → Utility messages we send / client / month (computed) | B11: =B9*B10 -> 100 | C11: =C9*C10 -> 150
A12: Marketing/promotional messages we send / client / month (0 if none planned) | B12: 0 | C12: 0
A14: Fixed infra cost per client
A15: Total fixed infra (Sheet 1) ÷ clients | B15: =IFERROR('1. Fixed Infra Costs'!C12/B6,0) -> 15.8 | C15: =IFERROR('1. Fixed Infra Costs'!D12/C6,0) -> 33.4005
A17: Variable cost per client
A18: AI generation cost (Sheet 2 — same both scenarios) | B18: ='2. AI Variable Costs'!F16 -> 317.84164 | C18: ='2. AI Variable Costs'!F16 -> 317.84164
A19: Storage cost (rate × avg GB, Sheet 3) | B19: =IFERROR('3. Other Per-Client Costs'!C5*B8,0) -> 14.3145 | C19: =IFERROR('3. Other Per-Client Costs'!D5*C8,0) -> 14.3145
A20: WhatsApp Utility cost (Sheet 3 rate × utility messages/client above) | B20: =IFERROR('3. Other Per-Client Costs'!$C$7*B11,0) -> 11.5 | C20: =IFERROR('3. Other Per-Client Costs'!$D$7*C11,0) -> 17.25
A21: WhatsApp Marketing cost (Sheet 3 rate × marketing messages/client above) | B21: =IFERROR('3. Other Per-Client Costs'!$C$8*B12,0) -> 0 | C21: =IFERROR('3. Other Per-Client Costs'!$D$8*C12,0) -> 0
A22: Razorpay processing fee (% of price) | B22: =IFERROR('3. Other Per-Client Costs'!C6*B7,0) -> 23.5764 | C22: =IFERROR('3. Other Per-Client Costs'!D6*C7,0) -> 23.5764
A24: Total Cost Per Client / Month | B24: =B15+B18+B19+B20+B21+B22 -> 383.03254 | C24: =C15+C18+C19+C20+C21+C22 -> 406.38304
A26: Revenue Per Client / Month | B26: =B7 -> 999 | C26: =C7 -> 999
A27: Margin Per Client (₹) | B27: =B26-B24 -> 615.96746 | C27: =C26-C24 -> 592.61696
A28: Margin Per Client (%) | B28: =IFERROR(B27/B26,0) -> 0.61658404 | C28: =IFERROR(C27/C26,0) -> 0.59321017
A30: Railway, Upstash, and Cloudflare R2 are all confirmed live, so the infra cost feeding both columns is real. The gap between these two columns now comes entirely from scale — more clients means the fixed infra cost splits thinner per client, while variable costs (AI, storage, WhatsApp) stay roughly flat per client regardless of scale. Update the inputs above any time you want to model a different client count or usage pattern.

Sheet 5. Open Decisions
A1: Business Decisions Waiting On You — Not On A Developer
A2: These are real contradictions found in the live code. Each one is a pricing or product decision, not a bug.
A4: What the code currently does | B4: Why it matters for pricing | C4: Your decision
A5: A MintCoin has no defined rupee value anywhere in the code — coins are granted (trial, monthly, membership), never sold at a fixed rate. | B5: You can't tell if a heavy-usage client is profitable or a loss until a coin has a real cost basis.
A6: Short-term access passes (₹299/₹499/₹799) unlock account access but grant zero MintCoins. | B6: If a pass-holder can't actually get creative work done, it's unclear what they're paying for.
A7: Storage add-ons are purchased using wallet cash balance — but the wallet UI is meant to stay hidden from clients in this phase. | B7: Right now, a client who needs more storage may have no working way to actually pay for it.
A8: A full freelancer marketplace model (wallet, escrow, 15–20% managed margin, 3–5% freelancer commission) is fully built and only hidden behind feature flags. | B8: This is a second, much more cash-heavy business sitting dormant. Decide if/when it turns back on, and whether it can coexist with MintCoins.
A9: Payout fee settings disagree in the code — one place says ₹49, another says ₹25 for instant payout. | B9: Any live payout flow right now would charge an inconsistent fee depending on which code path runs.
A10: Mock payment checkout (PAYMENT_MOCK_CHECKOUT) can activate a membership or access pass without a real Razorpay payment. | B10: Confirm this is off in production, or clients could get real access without real payment.
A11: No refund flow exists for real Razorpay payments — only internal wallet-based reversals. | B11: Decide what actually happens if a client wants their money back.
A12: No coupon, discount, or promo-code system exists anywhere. | B12: Any discounting today would have to be a manual admin action, not a real campaign tool.
A13: RESOLVED — Render has been fully retired. Backend now runs on Railway (Hobby plan), confirmed live with a passing healthcheck and all 4 background workers started cleanly in production logs. | B13: This is no longer an open decision — keeping it here as a record of what used to be true, so the history of the migration isn’t lost.
A14: RESOLVED — File storage migrated to Cloudflare R2. Verified: a real uploaded reference file shows correctly in the R2 dashboard with correct type, size, and private-bucket rules intact. | B14: Worth a final check: confirm avatars, kyc-docs, and job-attachments buckets show the same confirmed activity as mintbox-files before treating the full migration as complete across all file types.
